{
  "updated_at": "2026-07-05T00:34:48",
  "entries": [
    {
      "Source": "Apex Competition",
      "Product": "Audi Rsq8 Vorsprung Or Ps60000 Ps50K In Instant Wins 572026",
      "Price": "\u00a32.00",
      "Percent Sold": "25%",
      "Source URL": "",
      "URL": "https://apex-competition.co.uk/competition/audi-rsq8-vorsprung-or-ps60000-ps50k-in-instant-wins-572026"
    },
    {
      "Source": "Bikelifecompetitions",
      "Product": "Alpinestars SMX-6 V3 Drystar Boots",
      "Price": "\u00a31.99",
      "Percent Sold": "22%",
      "Source URL": "",
      "URL": "https://bikelifecompetitions.co.uk/shop/alpinestars-smx-6-v3-drystar-boots%f0%9f%91%8c/"
    },
    {
      "Source": "Bikelifecompetitions",
      "Product": "Hiplok DX1000",
      "Price": "\u00a31.89",
      "Percent Sold": "32%",
      "Source URL": "",
      "URL": "https://bikelifecompetitions.co.uk/shop/hiplok-dx1000%f0%9f%92%aa/"
    },
    {
      "Source": "Bikelifecompetitions",
      "Product": "Kawasaki ZX10R \u2013 30th Anniversary Edition",
      "Price": "\u00a32.99",
      "Percent Sold": "19%",
      "Source URL": "",
      "URL": "https://bikelifecompetitions.co.uk/shop/kawasaki-zx10r-30th-anniversary-edition/"
    },
    {
      "Source": "Bikelifecompetitions",
      "Product": "Knox Handroid Pod Mk5 Gloves",
      "Price": "\u00a30.73",
      "Percent Sold": "19%",
      "Source URL": "",
      "URL": "https://bikelifecompetitions.co.uk/shop/knox-handroid-pod-mk5-gloves/"
    },
    {
      "Source": "Bikelifecompetitions",
      "Product": "Michelin Tyres Your Choice of Compound & Style",
      "Price": "\u00a31.99",
      "Percent Sold": "19%",
      "Source URL": "",
      "URL": "https://bikelifecompetitions.co.uk/shop/michelin-tyres-your-choice-of-compound-style%f0%9f%91%80/"
    },
    {
      "Source": "Bikelifecompetitions",
      "Product": "\u00a3250 worth of Royal Enfield tickets \u2013 49p",
      "Price": "\u00a30.49",
      "Percent Sold": "13%",
      "Source URL": "",
      "URL": "https://bikelifecompetitions.co.uk/shop/250-worth-of-royal-enfield-tickets-49p/"
    },
    {
      "Source": "Bikelifecompetitions",
      "Product": "\u00a3250 worth of Royal Enfield tickets \u2013 \u00a33",
      "Price": "\u00a33.00",
      "Percent Sold": "8%",
      "Source URL": "",
      "URL": "https://bikelifecompetitions.co.uk/shop/250-worth-of-royal-enfield-tickets-3/"
    },
    {
      "Source": "Bikelifecompetitions",
      "Product": "\u00a3250 worth of Royal Enfield tickets \u2013 \u00a35 Only 80 tickets available!",
      "Price": "\u00a35.00",
      "Percent Sold": "37%",
      "Source URL": "",
      "URL": "https://bikelifecompetitions.co.uk/shop/250-worth-of-royal-enfield-tickets-5-only-80-tickets-available/"
    },
    {
      "Source": "C4competitions",
      "Product": "Apple AirPods Max 2",
      "Price": "\u00a30.40",
      "Percent Sold": "18%",
      "Source URL": "",
      "URL": "https://c4competitions.co.uk/product/apple-airpods-max-2-5jul-2026"
    },
    {
      "Source": "C4competitions",
      "Product": "Apple MacBook Neo",
      "Price": "\u00a30.60",
      "Percent Sold": "23%",
      "Source URL": "",
      "URL": "https://c4competitions.co.uk/product/apple-airpods-pro-neo-5jul-2026"
    },
    {
      "Source": "C4competitions",
      "Product": "Canon 2000D DSLR + Lens Bundle",
      "Price": "\u00a30.50",
      "Percent Sold": "10%",
      "Source URL": "",
      "URL": "https://c4competitions.co.uk/product/canon-2000d-dslr-lens-bundle-5jul-2026"
    },
    {
      "Source": "C4competitions",
      "Product": "Louis Vuitton Neverfull MM",
      "Price": "\u00a30.60",
      "Percent Sold": "27%",
      "Source URL": "",
      "URL": "https://c4competitions.co.uk/product/louis-vuitton-neverfull-mm-5jul-2026"
    },
    {
      "Source": "C4competitions",
      "Product": "Range Rover Velar",
      "Price": "\u00a32.97",
      "Percent Sold": "27%",
      "Source URL": "",
      "URL": "https://c4competitions.co.uk/product/range-rover-velar-5jul-2026"
    },
    {
      "Source": "C4competitions",
      "Product": "\u00a32,000 Tax Free Cash",
      "Price": "\u00a32.00",
      "Percent Sold": "49%",
      "Source URL": "",
      "URL": "https://c4competitions.co.uk/product/2000-tax-free-cash-5jul-2026"
    },
    {
      "Source": "Calibreclub",
      "Product": "395 tickets. One Rolex Submariner Date. No extensions.",
      "Price": "\u00a337.50",
      "Percent Sold": "14%",
      "Source URL": "",
      "URL": "https://thecalibreclub.com/competition/rolex-sub/"
    },
    {
      "Source": "Competitionfox",
      "Product": "2 WINNERS WIN \u00a350 SITE CREDIT \u2013 AUTO WIN 05/07",
      "Price": "\u00a33.00",
      "Percent Sold": "7.58%",
      "Source URL": "",
      "URL": "https://www.competitionfox.com/competition/2-winners-win-50-site-credit-auto-win-05-07/"
    },
    {
      "Source": "Competitionfox",
      "Product": "3 WINNERS WIN \u00a350 WORTH OF SCRATCH CARDS- AUTO WIN 05/07",
      "Price": "\u00a32.00",
      "Percent Sold": "16.67%",
      "Source URL": "",
      "URL": "https://www.competitionfox.com/competition/3-winners-win-50-worth-of-scratch-cards-auto-win-05-07/"
    },
    {
      "Source": "Competitionfox",
      "Product": "Biodance Bundle-AUTO IWIN 05/07",
      "Price": "\u00a32.00",
      "Percent Sold": "25%",
      "Source URL": "",
      "URL": "https://www.competitionfox.com/competition/biodance-bundle-auto-iwin-05-07/"
    },
    {
      "Source": "Competitionfox",
      "Product": "CASH PACPOT INSTANTS- MAIN PRIZE \u00a3200 JACKPOT-AUTO WIN 05/07",
      "Price": "\u00a32.00",
      "Percent Sold": "28.95%",
      "Source URL": "",
      "URL": "https://www.competitionfox.com/competition/cash-pacpot-instants-main-prize-200-jackpot-auto-win-05-07/"
    },
    {
      "Source": "Competitionfox",
      "Product": "COMP FOX CASH \u00a3200 05/07 AUTO-WIN",
      "Price": "\u00a33.00",
      "Percent Sold": "16.54%",
      "Source URL": "",
      "URL": "https://www.competitionfox.com/competition/comp-fox-cash-200-05-07-auto-win/"
    },
    {
      "Source": "Competitionfox",
      "Product": "EVENING \u00a3100 SITE CREDIT-AUTO WIN 05/07",
      "Price": "\u00a33.00",
      "Percent Sold": "0%",
      "Source URL": "",
      "URL": "https://www.competitionfox.com/competition/evening-100-site-credit-auto-win-05-07-3/"
    },
    {
      "Source": "Competitionfox",
      "Product": "EVENING \u00a3300 CASH AUTO WIN 05/07",
      "Price": "\u00a33.00",
      "Percent Sold": "3%",
      "Source URL": "",
      "URL": "https://www.competitionfox.com/competition/evening-300-cash-auto-win-05-07-2/"
    },
    {
      "Source": "Competitionfox",
      "Product": "FOXY CHEAP AND CHEERFUL \u2013 10 MAIN JACKPOT WINNERS \u00a3100 -AUTO WIN 05/07",
      "Price": "\u00a30.10",
      "Percent Sold": "15.7%",
      "Source URL": "",
      "URL": "https://www.competitionfox.com/competition/foxy-cheap-and-cheerful-10-main-jackpot-winners-100-auto-win-05-07/"
    },
    {
      "Source": "Competitionfox",
      "Product": "Karcher WD 2 Plus Wet & Dry Corded Vacuum Cleaner-AUTO WIN 05/07",
      "Price": "\u00a32.00",
      "Percent Sold": "35.29%",
      "Source URL": "",
      "URL": "https://www.competitionfox.com/competition/karcher-wd-2-plus-wet-dry-corded-vacuum-cleaner-auto-win-05-07/"
    },
    {
      "Source": "Competitionfox",
      "Product": "Lego 40861 Brickheadz Sully, Mike and Boo Figures AUTO-WIN",
      "Price": "\u00a32.00",
      "Percent Sold": "19.23%",
      "Source URL": "",
      "URL": "https://www.competitionfox.com/competition/lego-40861-brickheadz-sully-mike-and-boo-figures-auto-win/"
    },
    {
      "Source": "Competitionfox",
      "Product": "MEAT MAN STEAK HAMPER PACK-AUTO WIN 05/07",
      "Price": "\u00a32.00",
      "Percent Sold": "44.62%",
      "Source URL": "",
      "URL": "https://www.competitionfox.com/competition/meat-man-steak-hamper-pack-auto-win-05-07/"
    },
    {
      "Source": "Competitionfox",
      "Product": "Meta Meta Quest 3S All-In-One Mixed Reality Headset and Controllers, 256GB, White AUTO-WIN 05/07",
      "Price": "\u00a34.00",
      "Percent Sold": "13.54%",
      "Source URL": "",
      "URL": "https://www.competitionfox.com/competition/meta-meta-quest-3s-all-in-one-mixed-reality-headset-and-controllers-256gb-white-auto-win-05-07/"
    },
    {
      "Source": "Competitionfox",
      "Product": "MIDDAY WIN \u00a350 SITE CREDIT \u2013AUTO-WIN 05/07",
      "Price": "\u00a32.00",
      "Percent Sold": "0%",
      "Source URL": "",
      "URL": "https://www.competitionfox.com/competition/midday-win-50-site-credit-auto-win-05-07/"
    },
    {
      "Source": "Competitionfox",
      "Product": "MIDDAY \u00a3115 CASH AUTO WIN 05/07",
      "Price": "\u00a33.00",
      "Percent Sold": "3.95%",
      "Source URL": "",
      "URL": "https://www.competitionfox.com/competition/midday-115-cash-auto-win-05-07/"
    },
    {
      "Source": "Competitionfox",
      "Product": "MORNING \u00a3100 SITE CREDIT-AUTO WIN 05/07",
      "Price": "\u00a33.00",
      "Percent Sold": "24.24%",
      "Source URL": "",
      "URL": "https://www.competitionfox.com/competition/morning-100-site-credit-auto-win-05-07-3/"
    },
    {
      "Source": "Competitionfox",
      "Product": "MORNING \u00a3300 CASH AUTO WIN 05/07",
      "Price": "\u00a33.00",
      "Percent Sold": "8.5%",
      "Source URL": "",
      "URL": "https://www.competitionfox.com/competition/morning-300-cash-auto-win-05-07-3/"
    },
    {
      "Source": "Competitionfox",
      "Product": "Playgo Fairy Unicorn Water Activity Table-AUTO WIN 05/07",
      "Price": "\u00a32.00",
      "Percent Sold": "51.43%",
      "Source URL": "",
      "URL": "https://www.competitionfox.com/competition/playgo-fairy-unicorn-water-activity-table-auto-win-05-07/"
    },
    {
      "Source": "Competitionfox",
      "Product": "SHARK CHILLPILL 3-IN-1 PERSONAL HIGH-SPEED FAN, ULTRA-FINE MIST AND INSTACHILL SYSTEM, INCLUDES 3 COOLING AUTO-WIN 05/07",
      "Price": "\u00a33.00",
      "Percent Sold": "85.06%",
      "Source URL": "",
      "URL": "https://www.competitionfox.com/competition/shark-chillpill-3-in-1-personal-high-speed-fan-ultra-fine-mist-and-instachill-system-includes-3-cooling-auto-win-04-07/"
    },
    {
      "Source": "Competitionfox",
      "Product": "SUNDAY INSTANT WINS- MAIN JACKPOT \u00a3100 CASH \u2013 AUTO WIN 05/07",
      "Price": "\u00a31.00",
      "Percent Sold": "19.75%",
      "Source URL": "",
      "URL": "https://www.competitionfox.com/competition/sunday-instant-wins-main-jackpot-100-cash-auto-win-05-07/"
    },
    {
      "Source": "Competitionfox",
      "Product": "WIN \u00a31000 CASH- 05/07",
      "Price": "\u00a32.00",
      "Percent Sold": "13%",
      "Source URL": "",
      "URL": "https://www.competitionfox.com/competition/win-1000-cash-05-07/"
    },
    {
      "Source": "Competitionfox",
      "Product": "WIN \u00a3150 CASH LOW ODDS \u2013AUTO WIN 05/07",
      "Price": "\u00a35.00",
      "Percent Sold": "21.67%",
      "Source URL": "",
      "URL": "https://www.competitionfox.com/competition/win-150-cash-low-odds-auto-win-05-07/"
    },
    {
      "Source": "Competitionfox",
      "Product": "WIN \u00a3200 IKEA GIFT CARD- 05/07",
      "Price": "\u00a30.50",
      "Percent Sold": "8.25%",
      "Source URL": "",
      "URL": "https://www.competitionfox.com/competition/win-200-ikea-gift-card-05-07/"
    },
    {
      "Source": "Competitionfox",
      "Product": "WIN \u00a3250 SUNDAY CASH \u2013 LOW ODDS \u2013 05/07-AUTO WIN",
      "Price": "\u00a35.00",
      "Percent Sold": "30%",
      "Source URL": "",
      "URL": "https://www.competitionfox.com/competition/win-250-sunday-cash-low-odds-05-07-auto-win/"
    },
    {
      "Source": "Competitionfox",
      "Product": "WIN \u00a3600 CASH- 05/07",
      "Price": "\u00a31.50",
      "Percent Sold": "9.78%",
      "Source URL": "",
      "URL": "https://www.competitionfox.com/competition/win-600-cash-05-07/"
    },
    {
      "Source": "Competitionfox",
      "Product": "Winner Picks one River Island Bag -AUTO WIN 05/07",
      "Price": "\u00a32.00",
      "Percent Sold": "2%",
      "Source URL": "",
      "URL": "https://www.competitionfox.com/competition/winner-picks-one-river-island-bag-auto-win-05-07/"
    },
    {
      "Source": "Competitionfox",
      "Product": "WINNER PICKS \u00a350 SUPERMARKET VOUCHER- AUTO WIN 05/07",
      "Price": "\u00a32.00",
      "Percent Sold": "10%",
      "Source URL": "",
      "URL": "https://www.competitionfox.com/competition/winner-picks-50-supermarket-voucher-auto-win-05-07/"
    },
    {
      "Source": "Competitionfox",
      "Product": "WONKY DONKEY \u2013 \u00a34,000 INSTANT WINS & 5 MAIN WINNERS WIN \u00a3100 CASH JACKPOTS-AUTO WIN-05/07",
      "Price": "\u00a30.35",
      "Percent Sold": "24.49%",
      "Source URL": "",
      "URL": "https://www.competitionfox.com/competition/wonky-donkey-4000-instant-wins-5-main-winners-win-100-cash-jackpots-auto-win-05-07/"
    },
    {
      "Source": "Competitionfox",
      "Product": "\u00a334,000 WORTH OF INSTANTS -MAIN PRIZE \u00a31,000 CASH JACKPOT \u2013 05/07-AUTO WIN",
      "Price": "\u00a33.00",
      "Percent Sold": "15.01%",
      "Source URL": "",
      "URL": "https://www.competitionfox.com/competition/34000-worth-of-instants-main-prize-1000-cash-jackpot-05-07-auto-win/"
    },
    {
      "Source": "Competitionfox",
      "Product": "\u00a350 AMAZON GIFT CARD-AUTO WIN 05/07",
      "Price": "\u00a32.00",
      "Percent Sold": "10%",
      "Source URL": "",
      "URL": "https://www.competitionfox.com/competition/50-amazon-gift-card-auto-win-05-07/"
    },
    {
      "Source": "Competitionfox",
      "Product": "\u00a3500 CASH JACKPOT + 3K WORTH OF INSTANT PRIZES -AUTO WIN 05/07",
      "Price": "\u00a30.10",
      "Percent Sold": "33.5%",
      "Source URL": "",
      "URL": "https://www.competitionfox.com/competition/500-cash-jackpot-3k-worth-of-instant-prizes-auto-win-05-07/"
    },
    {
      "Source": "Competitiongo",
      "Product": "10P PRIZE POP - \u00a3350 MAIN PRIZE + \u00a34,000 INSTANT WINS (RECENTLY ADDED)",
      "Price": "\u00a30.10",
      "Percent Sold": "29.91%",
      "Source URL": "",
      "URL": "https://competitiongo.co.uk/competition-detail.php?competition=10p-prize-pop"
    },
    {
      "Source": "Competitiongo",
      "Product": "2 UNIQUE WINNERS: 151 BLOOMING WATERS COLLECTION BOX",
      "Price": "\u00a30.35",
      "Percent Sold": "34.32%",
      "Source URL": "",
      "URL": "https://competitiongo.co.uk/competition-detail.php?competition=2-unique-winners-151-blooming-waters"
    },
    {
      "Source": "Competitiongo",
      "Product": "2 UNIQUE WINNERS: 1ST PLACE - PRISMATIC EVOLUTIONS POKEMON CENTER ELITE TRAINER BOX / 2ND PLACE: PRISMATIC EVOLUTIONS ELITE TRAINER BOX",
      "Price": "\u00a30.35",
      "Percent Sold": "39.14%",
      "Source URL": "",
      "URL": "https://competitiongo.co.uk/competition-detail.php?competition=2-unique-winners-prismatic-evolutions"
    },
    {
      "Source": "Competitiongo",
      "Product": "FOUR UNIQUE GOLD WINNERS: 1ST - 2026 FULL SOVEREIGN / 2ND - 2026 HALF SOVEREIGN / 3RD & 4TH PLACE: 1G GOLD BAR + 35 GOLD AND SILVER BAR INSTANT WINS!",
      "Price": "\u00a31.99",
      "Percent Sold": "60.06%",
      "Source URL": "",
      "URL": "https://competitiongo.co.uk/competition-detail.php?competition=four-unique-gold-winners"
    },
    {
      "Source": "Competitiongo",
      "Product": "GRILLSTREAM STEALTH 4 BURNER HYBRID GAS BARBECUE + 10 MEAT HAMPER INSTANT WINS",
      "Price": "\u00a30.49",
      "Percent Sold": "40.51%",
      "Source URL": "",
      "URL": "https://competitiongo.co.uk/competition-detail.php?competition=grillstream-stealth-4-burner-hybrid-gas-barbecue-10-meat-hamper-instant-wins"
    },
    {
      "Source": "Competitiongo",
      "Product": "IPAD PRO + \u00a32,500 INSTANT WINS",
      "Price": "\u00a30.99",
      "Percent Sold": "29.31%",
      "Source URL": "",
      "URL": "https://competitiongo.co.uk/competition-detail.php?competition=ipad-pro-2500-instant-wins"
    },
    {
      "Source": "Competitiongo",
      "Product": "LEGO THE GOONIES",
      "Price": "\u00a30.30",
      "Percent Sold": "22.17%",
      "Source URL": "",
      "URL": "https://competitiongo.co.uk/competition-detail.php?competition=lego-the-goonies"
    },
    {
      "Source": "Competitiongo",
      "Product": "LEGO THE LORD OF THE RINGS: THE SHIRE",
      "Price": "\u00a30.30",
      "Percent Sold": "39.77%",
      "Source URL": "",
      "URL": "https://competitiongo.co.uk/competition-detail.php?competition=lego-the-lord-of-the-rings-the-shire"
    },
    {
      "Source": "Competitiongo",
      "Product": "LOST THUNDER ELITE TRAINER BOX IN ACRYLIC CASE + 55 SUN & MOON INSTANT WINS",
      "Price": "\u00a30.79",
      "Percent Sold": "38.6%",
      "Source URL": "",
      "URL": "https://competitiongo.co.uk/competition-detail.php?competition=lost-thunder-elite-trainer-box-in-acrylic-case-55-sun-moon-instant-wins"
    },
    {
      "Source": "Competitiongo",
      "Product": "OMALOS MATT BEIGE RATTAN EFFECT 4 SEATER COFFEE SET",
      "Price": "\u00a30.25",
      "Percent Sold": "21.68%",
      "Source URL": "",
      "URL": "https://competitiongo.co.uk/competition-detail.php?competition=omalos-matt-beige-rattan-effect-4-seater-coffee-set"
    },
    {
      "Source": "Competitiongo",
      "Product": "TEAM CURTIS VS TEAM CHRIS - WINNING TEAM RECEIVES 60% / LOSING TEAM RECEIVES 40% SHARE (READ DESCRIPTION) + \u00a35,000 INSTANT WINS!",
      "Price": "\u00a30.35",
      "Percent Sold": "100%",
      "Source URL": "",
      "URL": "https://competitiongo.co.uk/competition-detail.php?competition=team-curtis-vs-team-chris"
    },
    {
      "Source": "Competitiongo",
      "Product": "TWO UNIQUE WINNERS: \u00a3100 SITE CREDIT EACH!",
      "Price": "\u00a30.50",
      "Percent Sold": "46.88%",
      "Source URL": "",
      "URL": "https://competitiongo.co.uk/competition-detail.php?competition=two-unique-winners-100-site-credit-each-16"
    },
    {
      "Source": "Competitiongo",
      "Product": "XP DEUS II WITH WS6 ST HEADPHONES + 40 METAL DETECTING INSTANT WINS",
      "Price": "\u00a30.99",
      "Percent Sold": "34.79%",
      "Source URL": "",
      "URL": "https://competitiongo.co.uk/competition-detail.php?competition=xp-deus-ii-with-ws6-st-headphones-40-metal-detecting-instant-wins"
    },
    {
      "Source": "Cotswoldcompetitions",
      "Product": "5g Gold Bar",
      "Price": "\u00a31.17",
      "Percent Sold": "13.36%",
      "Source URL": "",
      "URL": "https://www.cotswoldcompetitions.co.uk/product/5g-gold-bar/"
    },
    {
      "Source": "Cotswoldcompetitions",
      "Product": "Cotswold Company Wern Stone Lamp",
      "Price": "\u00a30.47",
      "Percent Sold": "8%",
      "Source URL": "",
      "URL": "https://www.cotswoldcompetitions.co.uk/product/cotswold-company-wern-stone-lamp-2/"
    },
    {
      "Source": "Cotswoldcompetitions",
      "Product": "Cotswold Distillery Madeira Cask Single Malt Whisky",
      "Price": "\u00a30.17",
      "Percent Sold": "15.02%",
      "Source URL": "",
      "URL": "https://www.cotswoldcompetitions.co.uk/product/cotswold-distillery-madeira-cask-single-malt-whisky/"
    },
    {
      "Source": "Cotswoldcompetitions",
      "Product": "Daylesford Taste of the Cotswolds Hamper",
      "Price": "\u00a30.47",
      "Percent Sold": "6.4%",
      "Source URL": "",
      "URL": "https://www.cotswoldcompetitions.co.uk/product/daylesford-taste-of-the-cotswolds-hamper/"
    },
    {
      "Source": "Cotswoldcompetitions",
      "Product": "FairFax & Favor Regina Seude Heeled Boots",
      "Price": "\u00a30.97",
      "Percent Sold": "17.8%",
      "Source URL": "",
      "URL": "https://www.cotswoldcompetitions.co.uk/product/fairfax-favor-regina-seude-heeled-boots/"
    },
    {
      "Source": "Cotswoldcompetitions",
      "Product": "Fortnum & Mason The Cheese & Wine Hamper",
      "Price": "\u00a30.47",
      "Percent Sold": "21.96%",
      "Source URL": "",
      "URL": "https://www.cotswoldcompetitions.co.uk/product/fortnum-mason-the-cheese-wine-hamper/"
    },
    {
      "Source": "Cotswoldcompetitions",
      "Product": "Holland Cooper Country Fleece Gilet",
      "Price": "\u00a30.37",
      "Percent Sold": "24%",
      "Source URL": "",
      "URL": "https://www.cotswoldcompetitions.co.uk/product/holland-cooper-country-fleece-gilet/"
    },
    {
      "Source": "Cotswoldcompetitions",
      "Product": "Holland Cooper Monaco Sunglasses",
      "Price": "\u00a30.47",
      "Percent Sold": "25.43%",
      "Source URL": "",
      "URL": "https://www.cotswoldcompetitions.co.uk/product/holland-cooper-monaco-sunglasses/"
    },
    {
      "Source": "Cotswoldcompetitions",
      "Product": "Holland Cooper Soho Camera Bag",
      "Price": "\u00a30.67",
      "Percent Sold": "9.66%",
      "Source URL": "",
      "URL": "https://www.cotswoldcompetitions.co.uk/product/holland-cooper-soho-camera-bag/"
    },
    {
      "Source": "Cotswoldcompetitions",
      "Product": "Swatch x Omega Mission to Saturn",
      "Price": "\u00a30.67",
      "Percent Sold": "10.91%",
      "Source URL": "",
      "URL": "https://www.cotswoldcompetitions.co.uk/product/swatch-x-omega-mission-to-saturn/"
    },
    {
      "Source": "Daydreamdraws",
      "Product": "111 ANGEL NUMBERS INSTANT WINS",
      "Price": "\u00a30.50",
      "Percent Sold": "29%",
      "Source URL": "",
      "URL": "https://www.daydreamdraws.co.uk/competition/111-angel-numbers-instant-wins/"
    },
    {
      "Source": "Daydreamdraws",
      "Product": "DAYDREAM DRAWS WORLD CUP CASH INSTANT WINS",
      "Price": "\u00a30.79",
      "Percent Sold": "42%",
      "Source URL": "",
      "URL": "https://www.daydreamdraws.co.uk/competition/world-cup-cash-instant-wins/"
    },
    {
      "Source": "Diamondwinners",
      "Product": "1.99ct Diamond Ring! + \u00a35,000 in cash prizes!",
      "Price": "\u00a30.99",
      "Percent Sold": "26%",
      "Source URL": "",
      "URL": "https://diamondwinners.co.uk/product/1-99ct-diamond-ring-5000-in-cash-prizes/"
    },
    {
      "Source": "Diamondwinners",
      "Product": "The 3p Competition! - New Players Favourite!",
      "Price": "\u00a30.03",
      "Percent Sold": "20%",
      "Source URL": "",
      "URL": "https://diamondwinners.co.uk/product/the-3p-competition-new-players-favourite/"
    },
    {
      "Source": "Diamondwinners",
      "Product": "The \u00a310,000 Daily Dig Leaderboard! Top 3 Paid Daily!",
      "Price": "\u00a30.99",
      "Percent Sold": "15%",
      "Source URL": "",
      "URL": "https://diamondwinners.co.uk/product/the-10000-daily-dig-leaderboard-top-3-paid-daily-4/"
    },
    {
      "Source": "Diamondwinners",
      "Product": "Treasure Chest! - Interactive mini game!",
      "Price": "\u00a30.10",
      "Percent Sold": "17%",
      "Source URL": "",
      "URL": "https://diamondwinners.co.uk/product/treasure-chest-interactive-mini-game/"
    },
    {
      "Source": "EpicComps",
      "Product": "10k Scrather Instant Win Pot",
      "Price": "\u00a30.99",
      "Percent Sold": "8.3%",
      "Source URL": "",
      "URL": "https://epiccompetitions.co.uk/competition/10k-scrather-instant-win-pot-2"
    },
    {
      "Source": "EpicComps",
      "Product": "BMW X6M COMPETITION",
      "Price": "\u00a31.99",
      "Percent Sold": "16.5%",
      "Source URL": "",
      "URL": "https://epiccompetitions.co.uk/competition/bmw-x6m-competition"
    },
    {
      "Source": "EpicComps",
      "Product": "RING SPIN WIN \u00a31000",
      "Price": "\u00a30.50",
      "Percent Sold": "22.7%",
      "Source URL": "",
      "URL": "https://epiccompetitions.co.uk/competition/ring-spin-win-ps1000"
    },
    {
      "Source": "EpicComps",
      "Product": "Yes Sir I Can Boogie INSTANT WINS SPINS",
      "Price": "\u00a31.99",
      "Percent Sold": "5.8%",
      "Source URL": "",
      "URL": "https://epiccompetitions.co.uk/competition/yes-sir-i-can-boogie-instant-wins-spins"
    },
    {
      "Source": "Fireprizes",
      "Product": "1 Gram Gold Bar Fire Odds",
      "Price": "\u00a34.99",
      "Percent Sold": "",
      "Source URL": "",
      "URL": "https://fireprizes.co.uk/competition/1-gram-gold-bar-fire-odds"
    },
    {
      "Source": "Fireprizes",
      "Product": "Credit Crunch 8",
      "Price": "\u00a30.99",
      "Percent Sold": "",
      "Source URL": "",
      "URL": "https://fireprizes.co.uk/competition/credit-crunch-8"
    },
    {
      "Source": "Fireprizes",
      "Product": "Do You Wheely Like It 2",
      "Price": "\u00a30.60",
      "Percent Sold": "",
      "Source URL": "",
      "URL": "https://fireprizes.co.uk/competition/do-you-wheely-like-it-2"
    },
    {
      "Source": "Fireprizes",
      "Product": "Fifty Fifties 7",
      "Price": "\u00a31.49",
      "Percent Sold": "",
      "Source URL": "",
      "URL": "https://fireprizes.co.uk/competition/fifty-fifties-7"
    },
    {
      "Source": "Fireprizes",
      "Product": "Monthly Ps50 Giveaway July 2026",
      "Price": "\u00a30.00",
      "Percent Sold": "25%",
      "Source URL": "",
      "URL": "https://fireprizes.co.uk/competition/monthly-ps50-giveaway-july-2026"
    },
    {
      "Source": "Fireprizes",
      "Product": "Plinko",
      "Price": "\u00a30.55",
      "Percent Sold": "",
      "Source URL": "",
      "URL": "https://fireprizes.co.uk/competition/plinko"
    },
    {
      "Source": "Fireprizes",
      "Product": "Ring Doorbell Plus With Chime And Additional Quick Release Battery 2",
      "Price": "\u00a30.49",
      "Percent Sold": "",
      "Source URL": "",
      "URL": "https://fireprizes.co.uk/competition/ring-doorbell-plus-with-chime-and-additional-quick-release-battery-2"
    },
    {
      "Source": "Fireprizes",
      "Product": "Two Penny Falls 135",
      "Price": "\u00a30.02",
      "Percent Sold": "",
      "Source URL": "",
      "URL": "https://fireprizes.co.uk/competition/two-penny-falls-135"
    },
    {
      "Source": "Fireprizes",
      "Product": "Wheel Of Fire 13",
      "Price": "\u00a30.26",
      "Percent Sold": "",
      "Source URL": "",
      "URL": "https://fireprizes.co.uk/competition/wheel-of-fire-13"
    },
    {
      "Source": "Floridafun",
      "Product": "1P Penny Rush",
      "Price": "\u00a30.01",
      "Percent Sold": "8%",
      "Source URL": "",
      "URL": "https://ffc.uk/competitions/1p-penny-rush/"
    },
    {
      "Source": "Floridafun",
      "Product": "Squishmallow Instant Wins",
      "Price": "\u00a30.99",
      "Percent Sold": "4%",
      "Source URL": "",
      "URL": "https://ffc.uk/competitions/squishmallow-instant-wins/"
    },
    {
      "Source": "Jpraffles",
      "Product": "Lego Sranger Things \"The Creel House\" + \u00a31000 in instant wins + two bonus lego instant wins",
      "Price": "\u00a30.99",
      "Percent Sold": "20.1%",
      "Source URL": "",
      "URL": "https://jackpotraffles.co.uk/competition/lego-sranger-things-the-creel-house-ps1000-in-instant-wins-two-bonus-lego"
    },
    {
      "Source": "Lakedistrictgiveaways",
      "Product": "LDG Mystery Instant Wins",
      "Price": "\u00a30.01",
      "Percent Sold": "85.4%",
      "Source URL": "",
      "URL": "https://lakedistrictgiveaways.co.uk/competition/ldg-mystery-instant-wins"
    },
    {
      "Source": "Lakedistrictgiveaways",
      "Product": "Lodore Falls Spa Break",
      "Price": "\u00a33.00",
      "Percent Sold": "53.8%",
      "Source URL": "",
      "URL": "https://lakedistrictgiveaways.co.uk/competition/lodore-falls-spa-break"
    },
    {
      "Source": "Lakedistrictgiveaways",
      "Product": "Rolex 'Daytona' or \u00a312,500 - High Roller",
      "Price": "\u00a325.00",
      "Percent Sold": "28.8%",
      "Source URL": "",
      "URL": "https://lakedistrictgiveaways.co.uk/competition/rolex-daytona-or-12-500-high-roller"
    },
    {
      "Source": "Lakedistrictgiveaways",
      "Product": "Toy Story 5p Instant Wins",
      "Price": "\u00a30.05",
      "Percent Sold": "59.6%",
      "Source URL": "",
      "URL": "https://lakedistrictgiveaways.co.uk/competition/toy-story-5p-instant-wins"
    },
    {
      "Source": "Lakedistrictgiveaways",
      "Product": "WIN 50 TICKETS INTO THE DAYTONA - HIGH ROLLER",
      "Price": "\u00a325.00",
      "Percent Sold": "92%",
      "Source URL": "",
      "URL": "https://lakedistrictgiveaways.co.uk/competition/win-50-tickets-into-the-daytona-high-roller"
    },
    {
      "Source": "Lakedistrictgiveaways",
      "Product": "WIN 50 TICKETS INTO THE DAYTONA - HIGH ROLLER #2",
      "Price": "\u00a325.00",
      "Percent Sold": "0%",
      "Source URL": "",
      "URL": "https://lakedistrictgiveaways.co.uk/competition/win-50-tickets-into-the-daytona-high-roller-2"
    },
    {
      "Source": "Lakedistrictgiveaways",
      "Product": "\u00a31,000 for 10p",
      "Price": "\u00a30.10",
      "Percent Sold": "40.7%",
      "Source URL": "",
      "URL": "https://lakedistrictgiveaways.co.uk/competition/1-000-for-10p"
    },
    {
      "Source": "Lucky Tiger",
      "Product": "LAND ROVER DEFENDER - MINI DRAW",
      "Price": "\u00a30.50",
      "Percent Sold": "56.1%",
      "Source URL": "",
      "URL": "https://luckytigercompetitions.com/competition/defender-mini-draw"
    },
    {
      "Source": "Plumcompetitions",
      "Product": "#49 butchers box, Cambusbarron or cash alternative",
      "Price": "\u00a30.75",
      "Percent Sold": "",
      "Source URL": "",
      "URL": "https://www.plumcompetitions.co.uk/competition/49-butchers-box-cambusbarron/"
    },
    {
      "Source": "Premierprizecomps",
      "Product": "The Premier Prize Watch & Cash Giveaway",
      "Price": "\u00a37.99",
      "Percent Sold": "16%",
      "Source URL": "",
      "URL": "https://premierprizecompetitions.co.uk/competitions/5748481b-0763-45af-ae89-751acd17cd86"
    },
    {
      "Source": "Pura Vidacompetitions",
      "Product": "5p Spin to Win - Free Daily Spin!",
      "Price": "\u00a30.05",
      "Percent Sold": "60%",
      "Source URL": "",
      "URL": "https://pura-vidacompetitions.co.uk/product/5p-spin-to-win-free-daily-spin-4/"
    },
    {
      "Source": "Pura Vidacompetitions",
      "Product": "The \u00a380,000 Midas Touch | Match 3 To Win!",
      "Price": "\u00a32.50",
      "Percent Sold": "57%",
      "Source URL": "",
      "URL": "https://pura-vidacompetitions.co.uk/product/the-midas-touch-match-3-to-win%f0%9f%8e%b0/"
    },
    {
      "Source": "Rafflerays",
      "Product": "SUNDAY SERVICE",
      "Price": "\u00a31.49",
      "Percent Sold": "5%",
      "Source URL": "",
      "URL": "https://www.rafflerays.co.uk/competitions/sunday-service-copy-copy"
    },
    {
      "Source": "Rendallscompetitions",
      "Product": "WIN \u00a35,000 CASH!",
      "Price": "\u00a31.99",
      "Percent Sold": "12%",
      "Source URL": "",
      "URL": "https://rendallscompetitions.co.uk/product/%f0%9f%92%b7-win-5000-cash-%f0%9f%92%b7/"
    },
    {
      "Source": "Ruby Comps",
      "Product": "\u00a325 for 25p LOW ODDS AUTODRAW",
      "Price": "\u00a30.25",
      "Percent Sold": "45%",
      "Source URL": "",
      "URL": "https://rubycompetitions.co.uk/competition/ps25-for-25p-low-odds-autodraw-10"
    },
    {
      "Source": "Ryscompetitions",
      "Product": "Ry\u2019s Road To Riches \u2013 Win Tickets Into \u00a325,000 & \u00a310,000 Draws Instantly!",
      "Price": "\u00a30.10",
      "Percent Sold": "100%",
      "Source URL": "",
      "URL": "https://www.ryscompetitions.com/competition/rys-road-to-riches-win-tickets-into-25000-10000-draws-instantly/"
    },
    {
      "Source": "Tidetogethercompetitions",
      "Product": "20 X Arno-Hooks Leads",
      "Price": "\u00a31.99",
      "Percent Sold": "100%",
      "Source URL": "",
      "URL": "https://tidetogethercompetitions.com/competition/20-x-arno-hooks-leads/"
    }
  ]
}