{
  "updated_at": "2026-07-05T20:33:20",
  "entries": [
    {
      "Source": "7daysperformance",
      "Product": "50/50 Lamborghini Temerario Ticket Booster!",
      "Price": "\u00a30.49",
      "Percent Sold": "100%",
      "Source URL": "",
      "URL": "https://7daysperformance.co.uk/product/50-50-lamborghini-temerario-ticket-booster"
    },
    {
      "Source": "7daysperformance",
      "Product": "The Footy Fortune Frenzy #73!",
      "Price": "\u00a30.75",
      "Percent Sold": "9%",
      "Source URL": "",
      "URL": "https://7daysperformance.co.uk/product/instant-win-73"
    },
    {
      "Source": "7daysperformance",
      "Product": "The FREE Daily Instant Win! - \u00a3500 Site Credit End Prize!",
      "Price": "\u00a30.00",
      "Percent Sold": "47%",
      "Source URL": "",
      "URL": "https://7daysperformance.co.uk/product/win-sunday-free-050726"
    },
    {
      "Source": "7daysperformance",
      "Product": "Win A 1/2oz Gold Coin",
      "Price": "\u00a32.79",
      "Percent Sold": "40%",
      "Source URL": "",
      "URL": "https://7daysperformance.co.uk/product/win-a-1-2oz-gold-coin-6"
    },
    {
      "Source": "7daysperformance",
      "Product": "Win A 100ML Bottle Of Louis Vuitton Ombre Nomad!",
      "Price": "\u00a30.12",
      "Percent Sold": "74%",
      "Source URL": "",
      "URL": "https://7daysperformance.co.uk/product/win-a-100ml-bottle-of-louis-vuitton-ombre-nomad-6"
    },
    {
      "Source": "7daysperformance",
      "Product": "Win A Boss Grill Texas Outdoor Kitchen!",
      "Price": "\u00a30.25",
      "Percent Sold": "90%",
      "Source URL": "",
      "URL": "https://7daysperformance.co.uk/product/win-a-boss-grill-texas-outdoor-kitchen-4"
    },
    {
      "Source": "7daysperformance",
      "Product": "Win A Dyson Airwrap Multi-Styler & Dryer!",
      "Price": "\u00a30.19",
      "Percent Sold": "47%",
      "Source URL": "",
      "URL": "https://7daysperformance.co.uk/product/win-a-dyson-airwrap-multi-styler-dryer-2"
    },
    {
      "Source": "7daysperformance",
      "Product": "Win A Karcher Outdoor Bundle!",
      "Price": "\u00a30.49",
      "Percent Sold": "39%",
      "Source URL": "",
      "URL": "https://7daysperformance.co.uk/product/win-a-karcher-outdoor-bundle"
    },
    {
      "Source": "7daysperformance",
      "Product": "Win The All New iPhone 17 Pro or Pro Max #86!",
      "Price": "\u00a30.99",
      "Percent Sold": "51%",
      "Source URL": "",
      "URL": "https://7daysperformance.co.uk/product/win-the-all-new-iphone-17-pro-or-pro-max-86"
    },
    {
      "Source": "7daysperformance",
      "Product": "Win This 2026 Lamborghini Temerario + \u00a32,000 Cash!",
      "Price": "\u00a30.99",
      "Percent Sold": "46%",
      "Source URL": "",
      "URL": "https://7daysperformance.co.uk/product/win-lamborghini-temerario-050726"
    },
    {
      "Source": "7daysperformance",
      "Product": "Win This Ford Transit Custom MS-RT + \u00a32,000 Cash!",
      "Price": "\u00a30.33",
      "Percent Sold": "70%",
      "Source URL": "",
      "URL": "https://7daysperformance.co.uk/product/win-ford-msrt-050726"
    },
    {
      "Source": "7daysperformance",
      "Product": "Win This Honda CBR1000 Fireblade SP!",
      "Price": "\u00a30.45",
      "Percent Sold": "52%",
      "Source URL": "",
      "URL": "https://7daysperformance.co.uk/product/win-honda-fireblade-050726"
    },
    {
      "Source": "7daysperformance",
      "Product": "Win This Road Legal Sur Ron LBX Electric Bike!",
      "Price": "\u00a30.02",
      "Percent Sold": "65%",
      "Source URL": "",
      "URL": "https://7daysperformance.co.uk/product/win-surron-050726"
    },
    {
      "Source": "7daysperformance",
      "Product": "Win This Rolex GMT Master II 'Zombie'!",
      "Price": "\u00a30.15",
      "Percent Sold": "68%",
      "Source URL": "",
      "URL": "https://7daysperformance.co.uk/product/win-rolex-zombie-050726"
    },
    {
      "Source": "7daysperformance",
      "Product": "Win \u00a31,000 Tax Free Cash #84!",
      "Price": "\u00a30.05",
      "Percent Sold": "45%",
      "Source URL": "",
      "URL": "https://7daysperformance.co.uk/product/win-1-000-tax-free-cash-84"
    },
    {
      "Source": "7daysperformance",
      "Product": "Win \u00a31,250 Tax Free Cash #99!",
      "Price": "\u00a31.99",
      "Percent Sold": "39%",
      "Source URL": "",
      "URL": "https://7daysperformance.co.uk/product/win-1-250-tax-free-cash-99"
    },
    {
      "Source": "7daysperformance",
      "Product": "Win \u00a310,000 Tax Free Cash!",
      "Price": "\u00a30.02",
      "Percent Sold": "62%",
      "Source URL": "",
      "URL": "https://7daysperformance.co.uk/product/win-10-000-tax-free-cash-7"
    },
    {
      "Source": "7daysperformance",
      "Product": "Win \u00a32,500 Tax Free Cash!",
      "Price": "\u00a30.01",
      "Percent Sold": "50%",
      "Source URL": "",
      "URL": "https://7daysperformance.co.uk/product/win-2-500-tax-free-cash-7"
    },
    {
      "Source": "7daysperformance",
      "Product": "Win \u00a3500 Tax Free Cash #61!",
      "Price": "\u00a30.89",
      "Percent Sold": "52%",
      "Source URL": "",
      "URL": "https://7daysperformance.co.uk/product/win-500-tax-free-cash-61"
    },
    {
      "Source": "Apex66",
      "Product": "2019 Honda CRF250L HRC",
      "Price": "99p",
      "Percent Sold": "",
      "Source URL": "",
      "URL": "https://www.apex66.co.uk/competition/motorcycles/honda-crf250l-hrc/"
    },
    {
      "Source": "Apex66",
      "Product": "Bridgestone Tyres (Pair) \u2013 Your Choice of Tyres",
      "Price": "\u00a34.00",
      "Percent Sold": "",
      "Source URL": "",
      "URL": "https://www.apex66.co.uk/competition/motorcycle-clothing-accessories/bridgestone-tyres-pair-your-choice-of-tyres-2/"
    },
    {
      "Source": "Apex66",
      "Product": "Lenovo Idea Tab 11\u2033 Tablet with Keyboard",
      "Price": "\u00a32.00",
      "Percent Sold": "",
      "Source URL": "",
      "URL": "https://www.apex66.co.uk/competition/home-tech-lifestyle/lenovo-idea-tab-11-tablet-with-keyboard/"
    },
    {
      "Source": "Apex66",
      "Product": "Makita 12V Max Impact & Drill Driver Combo Kit with Batteries",
      "Price": "\u00a31.25",
      "Percent Sold": "",
      "Source URL": "",
      "URL": "https://www.apex66.co.uk/competition/garage-equipment-tools/makita-12v-max-impact-drill-driver-combo-kit-with-batteries-2/"
    },
    {
      "Source": "Apex66",
      "Product": "Mega Motorcycle Instant Win",
      "Price": "65p",
      "Percent Sold": "",
      "Source URL": "",
      "URL": "https://www.apex66.co.uk/competition/instant-wins/mega-motorcycle-instant-win-12/"
    },
    {
      "Source": "Apex66",
      "Product": "Merlin Airflow Kevlar Tech Jeans",
      "Price": "\u00a31.25",
      "Percent Sold": "",
      "Source URL": "",
      "URL": "https://www.apex66.co.uk/competition/motorcycle-clothing-accessories/merlin-airflow-kevlar-tech-jeans/"
    },
    {
      "Source": "Apex66",
      "Product": "Mystery Free Prize",
      "Price": "\u00a30.00",
      "Percent Sold": "",
      "Source URL": "",
      "URL": "https://www.apex66.co.uk/competition/free-competitions/mystery-free-prize-19/"
    },
    {
      "Source": "Apex66",
      "Product": "Odds Supercharger (1 in 5 wins) \u2013 200+ Instant Wins",
      "Price": "\u00a32.50",
      "Percent Sold": "",
      "Source URL": "",
      "URL": "https://www.apex66.co.uk/competition/instant-wins/odds-supercharger-1-in-5-wins-200-instant-wins-59/"
    },
    {
      "Source": "Apex66",
      "Product": "Richa Stradale Boots",
      "Price": "\u00a31.00",
      "Percent Sold": "",
      "Source URL": "",
      "URL": "https://www.apex66.co.uk/competition/motorcycle-clothing-accessories/richa-stradale-boots/"
    },
    {
      "Source": "Apex66",
      "Product": "Vertex Lite 130 Roof Tent with Integrated Foam Mattress & Foldawa...",
      "Price": "\u00a34.00",
      "Percent Sold": "",
      "Source URL": "",
      "URL": "https://www.apex66.co.uk/competition/home-tech-lifestyle/vertex-lite-130-roof-tent-with-integrated-foam-mattress-foldaway-ladder/"
    },
    {
      "Source": "Apex66",
      "Product": "WIN A PRIZE EVERYTIME",
      "Price": "\u00a32.00",
      "Percent Sold": "",
      "Source URL": "",
      "URL": "https://www.apex66.co.uk/competition/credit-ticket-bundles/win-a-prize-everytime-223/"
    },
    {
      "Source": "Apex66",
      "Product": "Win \u00a3500 Cashback",
      "Price": "29p",
      "Percent Sold": "",
      "Source URL": "",
      "URL": "https://www.apex66.co.uk/competition/credit-ticket-bundles/win-500-cashback-14/"
    },
    {
      "Source": "Ballsofthunder",
      "Product": "\u00a3500 SUNDAY FUNDAY only 50p",
      "Price": "\u00a30.50",
      "Percent Sold": "100%",
      "Source URL": "",
      "URL": "https://ballsofthunder.com/competition/500-sunday-funday-%f0%9f%98%8e-only-50p-%f0%9f%aa%b3/"
    },
    {
      "Source": "Big Beastie",
      "Product": "Quick.. Ticket Bundle Station \u2013 \u00a3100 Of Tickets into \u00a310k End Prize (Autodraw)",
      "Price": "\u00a3 0.01",
      "Percent Sold": "27%",
      "Source URL": "",
      "URL": "https://bigbeastiecompetitions.co.uk/competition/%f0%9f%95%b7%ef%b8%8f-quick-ticket-bundle-station-100-of-tickets-into-10k-end-prize-autodraw/"
    },
    {
      "Source": "Caledoniacompetitions",
      "Product": "Caledonias Diamond Mine",
      "Price": "\u00a30.35",
      "Percent Sold": "7%",
      "Source URL": "",
      "URL": "https://caledoniacompetitions.co.uk/competition/caledonias-diamond-mine"
    },
    {
      "Source": "Caledoniacompetitions",
      "Product": "Cocktail Cash Splash",
      "Price": "\u00a30.35",
      "Percent Sold": "14%",
      "Source URL": "",
      "URL": "https://caledoniacompetitions.co.uk/competition/cocktail-cash-splash"
    },
    {
      "Source": "Dream Cars",
      "Product": "FREE: \u00a3300 Tax Free Cash (Prize Doubled Over \u00a31 Spend on Tickets)",
      "Price": "FREE",
      "Percent Sold": "",
      "Source URL": "",
      "URL": "https://dreamcargiveaways.co.uk/competitions/free-300-tax-free-cash-prize-doubled-over-1-spend-on-ticke"
    },
    {
      "Source": "Dream Cars",
      "Product": "Win This 2022 AVT Transporter T6.1 Camper & \u00a32,000 or \u00a342,000 Tax Free",
      "Price": "\u00a30.06",
      "Percent Sold": "",
      "Source URL": "",
      "URL": "https://dreamcargiveaways.co.uk/competitions/win-this-2022-avt-transporter-t61-camper-2000-or-42000-tax-free"
    },
    {
      "Source": "Dream Cars",
      "Product": "Win this Apple IPad Pro and Apple Pencil Pro",
      "Price": "\u00a30.99",
      "Percent Sold": "",
      "Source URL": "",
      "URL": "https://dreamcargiveaways.co.uk/competitions/win-this-apple-ipad-pro-and-apple-pencil-pro-4e"
    },
    {
      "Source": "Dream Cars",
      "Product": "Win this BMW M3 Touring + Porsche GT4 & \u00a35,000 or \u00a3130,000 Tax Free",
      "Price": "\u00a30.15",
      "Percent Sold": "",
      "Source URL": "",
      "URL": "https://dreamcargiveaways.co.uk/competitions/win-this-bmw-m3-touring-porsche-gt4-5000-or-130000-tax-free"
    },
    {
      "Source": "Dream Cars",
      "Product": "Win this Garmin Venu 4 - 45mm",
      "Price": "\u00a30.99",
      "Percent Sold": "",
      "Source URL": "",
      "URL": "https://dreamcargiveaways.co.uk/competitions/win-this-garmin-venu-4-45mm-1p"
    },
    {
      "Source": "Dream Cars",
      "Product": "Win this HexClad Hybrid-Power Bundle",
      "Price": "\u00a30.99",
      "Percent Sold": "",
      "Source URL": "",
      "URL": "https://dreamcargiveaways.co.uk/competitions/win-this-hexclad-hybrid-power-bundle-1d"
    },
    {
      "Source": "Dream Cars",
      "Product": "Win this Rolex GMT Master-II 'Sprite' or \u00a312,000 Tax Free",
      "Price": "\u00a30.15",
      "Percent Sold": "",
      "Source URL": "",
      "URL": "https://dreamcargiveaways.co.uk/competitions/win-this-rolex-gmt-master-ii-sprite-2-2-2-2-2"
    },
    {
      "Source": "Dream Cars",
      "Product": "Win this Ultimate Detailing Bundle",
      "Price": "\u00a30.89",
      "Percent Sold": "",
      "Source URL": "",
      "URL": "https://dreamcargiveaways.co.uk/competitions/win-this-ultimate-detailing-bundle-5"
    },
    {
      "Source": "Dream Cars",
      "Product": "Win this Yamaha Raptor YFM 700R Quad & \u00a31,000 or \u00a38,000 Tax Free",
      "Price": "\u00a30.29",
      "Percent Sold": "",
      "Source URL": "",
      "URL": "https://dreamcargiveaways.co.uk/competitions/win-this-yamaha-raptor-yfm-700r-quad-1000-or-8000-tax-free-3"
    },
    {
      "Source": "Dream Cars",
      "Product": "Win \u00a31,500 Tax Free Cash + Bonus Draw",
      "Price": "\u00a31.99",
      "Percent Sold": "",
      "Source URL": "",
      "URL": "https://dreamcargiveaways.co.uk/competitions/win-1500-tax-free-cash-bonus-draw-2o"
    },
    {
      "Source": "Dream Cars",
      "Product": "Win \u00a325,000 Tax Free Cash",
      "Price": "\u00a30.08",
      "Percent Sold": "",
      "Source URL": "",
      "URL": "https://dreamcargiveaways.co.uk/competitions/win-25000-tax-free-cash-2025-2g"
    },
    {
      "Source": "Dream Cars",
      "Product": "Win \u00a33,000 Tax Free Cash",
      "Price": "\u00a30.89",
      "Percent Sold": "",
      "Source URL": "",
      "URL": "https://dreamcargiveaways.co.uk/competitions/win-3000-tax-free-cash-4k-2"
    },
    {
      "Source": "Dreamtech",
      "Product": "100s & 1,000s 20p Instants l \u00a324,050 Instant Cash Upto \u00a31,000 l  \u00a3250 End Prize",
      "Price": "\u00a30.20",
      "Percent Sold": "",
      "Source URL": "",
      "URL": "https://dreamtechcompetitions.co.uk/competition/100s-1000s-20p-instants-l-24050-instant-cash-upto-1000-l-250-end-prize/"
    },
    {
      "Source": "Dreamtech",
      "Product": "WIN a BMW M135i or \u00a320,000 l OVER \u00a3400k in Prizes l 50/50 Every Other Ticket WINS",
      "Price": "\u00a33.95",
      "Percent Sold": "",
      "Source URL": "",
      "URL": "https://dreamtechcompetitions.co.uk/competition/win-a-bmw-m135i-or-20000-l-over-400k-in-prizes-l-50-50-every-other-ticket-wins/"
    },
    {
      "Source": "Eacompetitions",
      "Product": "HARLEY DAVIDSON XL 1200 CX ROADSTER + INSTANT WINS",
      "Price": "\u00a32.99",
      "Percent Sold": "29%",
      "Source URL": "",
      "URL": "https://eacompetitions.co.uk/prizes/harley-davidson-xl-1200-cx-roadster-instant-wins"
    },
    {
      "Source": "Fullswing",
      "Product": "#3 WIN A DRIVER OF YOUR CHOICE!",
      "Price": "0.75",
      "Percent Sold": "",
      "Source URL": "",
      "URL": "https://fullswingcomps.com/competition/3-win-a-driver-of-your-choice-3"
    },
    {
      "Source": "Fullswing",
      "Product": "LOOT BOXES",
      "Price": "0.45",
      "Percent Sold": "",
      "Source URL": "",
      "URL": "https://fullswingcomps.com/competition/loot-boxes"
    },
    {
      "Source": "Fullswing",
      "Product": "OFF THE COURSE PRIZES",
      "Price": "1.99",
      "Percent Sold": "",
      "Source URL": "",
      "URL": "https://fullswingcomps.com/competition/off-the-course-prizes"
    },
    {
      "Source": "Giveaway Guys",
      "Product": "A GRAND IN YOUR HAND - \u00a31000 Cash5th July 26",
      "Price": "\u00a30.20",
      "Percent Sold": "",
      "Source URL": "",
      "URL": "https://thegiveawayguys.co.uk/collections/competition/products/a-grand-in-your-hand-1000-cash-67"
    },
    {
      "Source": "Giveaway Guys",
      "Product": "Automatic Toyota Aygo- Affordable Daily",
      "Price": "\u00a31.50",
      "Percent Sold": "",
      "Source URL": "",
      "URL": "https://thegiveawayguys.co.uk/collections/competition/products/automatic-toyota-aygo"
    },
    {
      "Source": "Giveaway Guys",
      "Product": "Brand New Jeep Avenger + Tent Box 2.0",
      "Price": "\u00a32.75",
      "Percent Sold": "",
      "Source URL": "",
      "URL": "https://thegiveawayguys.co.uk/collections/competition/products/brand-new-jeep-avenger-tent-box"
    },
    {
      "Source": "Giveaway Guys",
      "Product": "eufy Video Doorbell5th July 26",
      "Price": "\u00a31.50",
      "Percent Sold": "",
      "Source URL": "",
      "URL": "https://thegiveawayguys.co.uk/collections/competition/products/eufy-video-doorbell-6"
    },
    {
      "Source": "Giveaway Guys",
      "Product": "Gold Bullion Bar 5g5th July 26",
      "Price": "\u00a31.99",
      "Percent Sold": "",
      "Source URL": "",
      "URL": "https://thegiveawayguys.co.uk/collections/competition/products/gold-bullion-bar-5g-2"
    },
    {
      "Source": "Giveaway Guys",
      "Product": "HexClad 6pc Japanese Damascus Steel Knife Set w/ Magnetic Knife Block5th July 26",
      "Price": "\u00a31.99",
      "Percent Sold": "",
      "Source URL": "",
      "URL": "https://thegiveawayguys.co.uk/collections/competition/products/hexclad-6pc-japanese-damascus-steel-knife-set-w-magnetic-knife-block-5"
    },
    {
      "Source": "Giveaway Guys",
      "Product": "iPhone 17 PRO 256GB - Any Colour5th July 26",
      "Price": "\u00a30.95",
      "Percent Sold": "",
      "Source URL": "",
      "URL": "https://thegiveawayguys.co.uk/collections/competition/products/iphone-17-pro-256gb-any-colour-18"
    },
    {
      "Source": "Giveaway Guys",
      "Product": "LEGO technic McLaren MCL39 F1 Car5th July 26",
      "Price": "\u00a31.99",
      "Percent Sold": "",
      "Source URL": "",
      "URL": "https://thegiveawayguys.co.uk/collections/competition/products/lego-technic-mclaren-mcl39-f1-car-3"
    },
    {
      "Source": "Giveaway Guys",
      "Product": "RAY-BAN Meta Wayfarer (Gen 2) Glasses5th July 26",
      "Price": "\u00a31.47",
      "Percent Sold": "",
      "Source URL": "",
      "URL": "https://thegiveawayguys.co.uk/collections/competition/products/ray-ban-meta-wayfarer-gen-2-glasses-2"
    },
    {
      "Source": "Giveaway Guys",
      "Product": "SMEG Kettle & Toaster - Any Colour*5th July 26",
      "Price": "\u00a31.99",
      "Percent Sold": "",
      "Source URL": "",
      "URL": "https://thegiveawayguys.co.uk/collections/competition/products/smeg-kettle-toaster-any-colour-11"
    },
    {
      "Source": "Giveaway Guys",
      "Product": "Sony PS5 + Toshiba 55\" 4K TV MEGA BUNDLE5th July 26",
      "Price": "\u00a30.79",
      "Percent Sold": "",
      "Source URL": "",
      "URL": "https://thegiveawayguys.co.uk/collections/competition/products/sony-ps5-toshiba-55-4k-tv-mega-bundle-24"
    },
    {
      "Source": "Giveaway Guys",
      "Product": "\u00a32,500 Tax Free Cash6th July 26",
      "Price": "\u00a30.70",
      "Percent Sold": "",
      "Source URL": "",
      "URL": "https://thegiveawayguys.co.uk/collections/competition/products/2-500-tax-free-cash-33"
    },
    {
      "Source": "Giveaway Guys",
      "Product": "\u00a3250 John Lewis Gift Card5th July 26",
      "Price": "\u00a30.99",
      "Percent Sold": "",
      "Source URL": "",
      "URL": "https://thegiveawayguys.co.uk/collections/competition/products/250-john-lewis-gift-card-4"
    },
    {
      "Source": "Hot Comps",
      "Product": "100 Tickets Into Kamado Big Joe\u2122 Grill - Series 3 + \u00a318,000 Instant Wins",
      "Price": "",
      "Percent Sold": "",
      "Source URL": "",
      "URL": "https://hotcomps.com/product/100-tickets-into-kamado-big-joe-grill-series-3-18000-instant-wins-2/"
    },
    {
      "Source": "Hot Comps",
      "Product": "5g Gold Bar",
      "Price": "",
      "Percent Sold": "",
      "Source URL": "",
      "URL": "https://hotcomps.com/product/5g-gold-bar-4/"
    },
    {
      "Source": "Hot Comps",
      "Product": "APP EXCLUSIVE! Win up to \u00a3100 Site Credit",
      "Price": "",
      "Percent Sold": "",
      "Source URL": "",
      "URL": "https://hotcomps.com/product/app-exclusive-win-up-to-100-site-credit-41/"
    },
    {
      "Source": "Hot Comps",
      "Product": "Ascended Heroes Pokemon Center Elite Trainer Box",
      "Price": "",
      "Percent Sold": "",
      "Source URL": "",
      "URL": "https://hotcomps.com/product/ascended-heroes-pokemon-center-elite-trainer-box/"
    },
    {
      "Source": "Hot Comps",
      "Product": "Bambu Lab X2D with AMS2 Pro",
      "Price": "",
      "Percent Sold": "",
      "Source URL": "",
      "URL": "https://hotcomps.com/product/bambu-lab-x2d-with-ams2-pro-3/"
    },
    {
      "Source": "Hot Comps",
      "Product": "BULL'S NL ADVANTAGE BLACK PROFESSIONAL DARTBOARD",
      "Price": "",
      "Percent Sold": "",
      "Source URL": "",
      "URL": "https://hotcomps.com/product/bulls-nl-advantage-black-professional-dartboard-3/"
    },
    {
      "Source": "Hot Comps",
      "Product": "JellyCat Munro Scottie Dog (Big)",
      "Price": "",
      "Percent Sold": "",
      "Source URL": "",
      "URL": "https://hotcomps.com/product/jellycat-munro-scottie-dog-big-3/"
    },
    {
      "Source": "Hot Comps",
      "Product": "Kamado Big Joe\u2122 Grill - Series 3 + \u00a318,000 Instant Wins",
      "Price": "",
      "Percent Sold": "",
      "Source URL": "",
      "URL": "https://hotcomps.com/product/kamado-big-joe-grill-series-3-18000-instant-wins/"
    },
    {
      "Source": "Hot Comps",
      "Product": "Pok\u00e9mon TCG Mega Evolution-Ascended Heroes Booster Pack Instant Win!",
      "Price": "",
      "Percent Sold": "",
      "Source URL": "",
      "URL": "https://hotcomps.com/product/pokemon-tcg-mega-evolution-ascended-heroes-booster-pack-instant-win/"
    },
    {
      "Source": "Hot Comps",
      "Product": "Shark ChillPill 3-in-1 Fan, Mist & InstaChill System",
      "Price": "",
      "Percent Sold": "",
      "Source URL": "",
      "URL": "https://hotcomps.com/product/shark-chillpill-3-in-1-fan-mist-instachill-system-9/"
    },
    {
      "Source": "Hot Comps",
      "Product": "Umbreon ex PSA 10 217/187 Japanese",
      "Price": "",
      "Percent Sold": "",
      "Source URL": "",
      "URL": "https://hotcomps.com/product/umbreon-ex-psa-10-217-187-japanese/"
    },
    {
      "Source": "Hot Comps",
      "Product": "Warhammer 40K Grey Knights Bundle",
      "Price": "",
      "Percent Sold": "",
      "Source URL": "",
      "URL": "https://hotcomps.com/product/warhammer-40k-grey-knights-bundle/"
    },
    {
      "Source": "Hot Comps",
      "Product": "\u00a31,000 Cash",
      "Price": "",
      "Percent Sold": "",
      "Source URL": "",
      "URL": "https://hotcomps.com/product/1000-cash-22/"
    },
    {
      "Source": "Hot Comps",
      "Product": "\u00a3250 Site Credit",
      "Price": "",
      "Percent Sold": "",
      "Source URL": "",
      "URL": "https://hotcomps.com/product/250-site-credit-19/"
    },
    {
      "Source": "Jammy",
      "Product": "AMAZON KINDLE 16GB or \u00a395 CASH!",
      "Price": "\u00a31.99",
      "Percent Sold": "",
      "Source URL": "",
      "URL": "https://jammy.co.uk/competition/card-15"
    },
    {
      "Source": "Jammy",
      "Product": "SUMMER \u00a3121,000 INSTANT WIN!",
      "Price": "\u00a30.99",
      "Percent Sold": "",
      "Source URL": "",
      "URL": "https://jammy.co.uk/competition/card-1"
    },
    {
      "Source": "Jammy",
      "Product": "SUMMER \u00a3121,000 INSTANT WIN!",
      "Price": "\u00a30.99",
      "Percent Sold": "",
      "Source URL": "",
      "URL": "https://jammy.co.uk/competition/card-13"
    },
    {
      "Source": "Jammy",
      "Product": "\u00a31000 INSTANT CASH + NEIGHBOURS!",
      "Price": "\u00a30.10",
      "Percent Sold": "",
      "Source URL": "",
      "URL": "https://jammy.co.uk/competition/card-14"
    },
    {
      "Source": "Lavishlife",
      "Product": "FREE DAILY INSTANT WIN COMP! WIN CASH & CREDIT FOR FREE#275",
      "Price": "\u00a3 0.00",
      "Percent Sold": "",
      "Source URL": "",
      "URL": "https://lavishlifecompetitions.co.uk/competition/free-daily-instant-win-comp-win-cash-credit-for-free275/"
    },
    {
      "Source": "Lavishlife",
      "Product": "FREE ENTRY \u2013 FAMILY DISNEYLAND PARIS TRIP!",
      "Price": "\u00a3 0.00",
      "Percent Sold": "",
      "Source URL": "",
      "URL": "https://lavishlifecompetitions.co.uk/competition/free-entry-family-disneyland-paris-trip-2/"
    },
    {
      "Source": "Lavishlife",
      "Product": "LAVISH CREDIT INSTANT WINS + \u00a3500 CREDIT END PRIZE!#38",
      "Price": "\u00a3 0.49",
      "Percent Sold": "",
      "Source URL": "",
      "URL": "https://lavishlifecompetitions.co.uk/competition/lavish-credit-instant-wins-500-credit-end-prize38/"
    },
    {
      "Source": "Lavishlife",
      "Product": "MORE PRIZES ADDED : PRIZE EVERYTIME DAILY EDITION! *SUNDAY 05.07.26*",
      "Price": "\u00a3 1.99",
      "Percent Sold": "",
      "Source URL": "",
      "URL": "https://lavishlifecompetitions.co.uk/competition/more-prizes-added-prize-everytime-daily-edition-sunday-05-07-26/"
    },
    {
      "Source": "Lavishlife",
      "Product": "OPEN THE SAFE INSTANTS : WIN UP TO \u00a35000 INSTANTLY \u2013 NEW SAFE FEATURE!",
      "Price": "\u00a3 0.99",
      "Percent Sold": "",
      "Source URL": "",
      "URL": "https://lavishlifecompetitions.co.uk/competition/open-the-safe-instants-win-up-to-5000-instantly-500-end-prize/"
    },
    {
      "Source": "Lavishlife",
      "Product": "PIKACHU EX 277/217 ACE 10 POK\u00c9MON CARD!",
      "Price": "\u00a3 0.20",
      "Percent Sold": "",
      "Source URL": "",
      "URL": "https://lavishlifecompetitions.co.uk/competition/pikachu-ex-277-217-ace-10-pokemon-card/"
    },
    {
      "Source": "Lavishlife",
      "Product": "PRIZE EVERYTIME SCRATCH CARD : WIN UP TO \u00a32,000 INSTANTLY- \u00a31K END PRIZE!#9",
      "Price": "\u00a3 10.00",
      "Percent Sold": "",
      "Source URL": "",
      "URL": "https://lavishlifecompetitions.co.uk/competition/prize-everytime-scratch-card-win-up-to-2000-instantly-1k-end-prize9/"
    },
    {
      "Source": "Lavishlife",
      "Product": "ROLEX BATMAN OR \u00a38,000 CASH!",
      "Price": "\u00a3 0.15",
      "Percent Sold": "",
      "Source URL": "",
      "URL": "https://lavishlifecompetitions.co.uk/competition/rolex-batman-or-8000-cash-2/"
    },
    {
      "Source": "Lavishlife",
      "Product": "SHARK TURBOBLADE TOWER FAN!",
      "Price": "\u00a3 0.20",
      "Percent Sold": "",
      "Source URL": "",
      "URL": "https://lavishlifecompetitions.co.uk/competition/shark-turboblade-tower-fan/"
    },
    {
      "Source": "Lavishlife",
      "Product": "THE CLAW : VOLUME 4 #26",
      "Price": "\u00a3 0.29",
      "Percent Sold": "",
      "Source URL": "",
      "URL": "https://lavishlifecompetitions.co.uk/competition/the-claw-volume-4-26/"
    },
    {
      "Source": "Lavishlife",
      "Product": "ULTIMATE PRIZE WHEEL BONANZA \u2013 20 DIFFERENT PRIZES \u2013 WHICH 1 WILL YOU LAND?!#6",
      "Price": "\u00a3 0.99",
      "Percent Sold": "",
      "Source URL": "",
      "URL": "https://lavishlifecompetitions.co.uk/competition/ultimate-prize-wheel-bonanza-20-different-prizes-which-1-will-you-land6/"
    },
    {
      "Source": "Lavishlife",
      "Product": "WIN 2000 ENTRIES INTO AUDI Q3 COMP!#2",
      "Price": "\u00a3 0.49",
      "Percent Sold": "",
      "Source URL": "",
      "URL": "https://lavishlifecompetitions.co.uk/competition/win-2000-entries-into-audi-q3-comp2/"
    },
    {
      "Source": "Lavishlife",
      "Product": "WIN EXTRA TICKETS INTO ROLEX BATMAN COMP \u2013 ODDS BOOSTER \u2013 1000 TICKETS END PRIZE!",
      "Price": "\u00a3 0.10",
      "Percent Sold": "",
      "Source URL": "",
      "URL": "https://lavishlifecompetitions.co.uk/competition/win-extra-tickets-into-rolex-batman-comp-odds-booster/"
    },
    {
      "Source": "Lowcostcompetitions",
      "Product": "Mega MTG 10k Mash up!",
      "Price": "\u00a30.99",
      "Percent Sold": "28%",
      "Source URL": "",
      "URL": "https://lowcostcompetitions.co.uk/competitions/mega-mtg-10k-mash-up"
    },
    {
      "Source": "Lucky Escape",
      "Product": "Berlin",
      "Price": "\u00a31.00",
      "Percent Sold": "",
      "Source URL": "",
      "URL": "https://www.luckyescapecompetitions.co.uk/competitions/berlin/"
    },
    {
      "Source": "Lucky Escape",
      "Product": "MARRAKECH",
      "Price": "\u00a32.00",
      "Percent Sold": "",
      "Source URL": "",
      "URL": "https://www.luckyescapecompetitions.co.uk/competitions/marrakech/"
    },
    {
      "Source": "Lucky Escape",
      "Product": "\u00a3200 site credit",
      "Price": "\u00a30.50",
      "Percent Sold": "",
      "Source URL": "",
      "URL": "https://www.luckyescapecompetitions.co.uk/competitions/200-site-credit-3/"
    },
    {
      "Source": "Luxuriousgiveaways",
      "Product": "Angel Number Bonanza 2",
      "Price": "\u00a32.99",
      "Percent Sold": "43%",
      "Source URL": "",
      "URL": "https://luxuriousgiveaways.com/competition/angel-number-bonanza-2"
    },
    {
      "Source": "Luxuriousgiveaways",
      "Product": "Garden Bundle",
      "Price": "\u00a30.99",
      "Percent Sold": "43%",
      "Source URL": "",
      "URL": "https://luxuriousgiveaways.com/competition/garden-bundle"
    },
    {
      "Source": "Luxuriousgiveaways",
      "Product": "Ps1500 Cash 212",
      "Price": "\u00a32.99",
      "Percent Sold": "43%",
      "Source URL": "",
      "URL": "https://luxuriousgiveaways.com/competition/ps1500-cash-212"
    },
    {
      "Source": "Luxuriousgiveaways",
      "Product": "Win Apple Iphone 17Pro12",
      "Price": "\u00a32.99",
      "Percent Sold": "43%",
      "Source URL": "",
      "URL": "https://luxuriousgiveaways.com/competition/win-apple-iphone-17pro12"
    },
    {
      "Source": "Magma",
      "Product": "MASSIVE 50G GOLD BAR OR \u00a35000 CASH ONLY 399 TICKETS",
      "Price": "\u00a325.00",
      "Percent Sold": "44.11%",
      "Source URL": "",
      "URL": "https://magmacomps.co.uk/competition/massive-50g-gold-bar-or-5000-cash-only-399-tickets/"
    },
    {
      "Source": "Magma",
      "Product": "ODDS BOOSTER WIN TICKETS INTO UPCOMING DRAWS 05.07.26",
      "Price": "\u00a30.25",
      "Percent Sold": "12.37%",
      "Source URL": "",
      "URL": "https://magmacomps.co.uk/competition/odds-booster-win-tickets-into-upcoming-draws-05-07-26/"
    },
    {
      "Source": "Magma",
      "Product": "WIN 10 TICKETS INTO 50G GOLD BAR OR \u00a35000 CASH 05.07.26 WORTH \u00a3250 #2",
      "Price": "\u00a32.00",
      "Percent Sold": "100%",
      "Source URL": "",
      "URL": "https://magmacomps.co.uk/competition/win-10-tickets-into-50g-gold-bar-or-5000-cash-05-07-26-worth-250-2/"
    },
    {
      "Source": "Magma",
      "Product": "WIN 10 TICKETS INTO 50G GOLD BAR OR \u00a35000 CASH 05.07.26 WORTH \u00a3250 #3",
      "Price": "\u00a32.00",
      "Percent Sold": "37%",
      "Source URL": "",
      "URL": "https://magmacomps.co.uk/competition/win-10-tickets-into-50g-gold-bar-or-5000-cash-05-07-26-worth-250-3/"
    },
    {
      "Source": "Magma",
      "Product": "WIN 10 TICKETS INTO 50G GOLD BAR OR \u00a35000 CASH 05.07.26 WORTH \u00a3250 #4",
      "Price": "\u00a32.00",
      "Percent Sold": "5.5%",
      "Source URL": "",
      "URL": "https://magmacomps.co.uk/competition/win-10-tickets-into-50g-gold-bar-or-5000-cash-05-07-26-worth-250-4/"
    },
    {
      "Source": "Magma",
      "Product": "WIN 100ML TOM FORD OMRBE LEATHER PARFUM",
      "Price": "\u00a30.25",
      "Percent Sold": "34.33%",
      "Source URL": "",
      "URL": "https://magmacomps.co.uk/competition/win-100ml-tom-ford-omrbe-leather-parfum/"
    },
    {
      "Source": "Magma",
      "Product": "WIN 500G SILVER BAR OR \u00a3800 CASH 05.07.26",
      "Price": "\u00a31.99",
      "Percent Sold": "23.82%",
      "Source URL": "",
      "URL": "https://magmacomps.co.uk/competition/win-500g-silver-bar-or-800-cash-05-07-26/"
    },
    {
      "Source": "Magma",
      "Product": "WIN APPLE AIRPOD PROS LATEST GENERATION 05.07.26",
      "Price": "\u00a30.50",
      "Percent Sold": "18.42%",
      "Source URL": "",
      "URL": "https://magmacomps.co.uk/competition/win-apple-airpod-pros-latest-generation-05-07-26/"
    },
    {
      "Source": "Magma",
      "Product": "WIN BRAND NEW APPLE IPHONE 17 PRO 05.07.26",
      "Price": "\u00a30.99",
      "Percent Sold": "27.56%",
      "Source URL": "",
      "URL": "https://magmacomps.co.uk/competition/win-brand-new-apple-iphone-17-pro-05-07-26/"
    },
    {
      "Source": "Magma",
      "Product": "WIN LOUIS VUITTON NEVERFULL GM TOTE BAG 05.07.26",
      "Price": "\u00a31.99",
      "Percent Sold": "27.31%",
      "Source URL": "",
      "URL": "https://magmacomps.co.uk/competition/win-louis-vuitton-neverfull-gm-tote-bag-05-07-26/"
    },
    {
      "Source": "Monstergiveaways",
      "Product": "Spin To Win - Daily Freebie 54",
      "Price": "Free",
      "Percent Sold": "71%",
      "Source URL": "",
      "URL": "https://monstergiveaways.co.uk/competition/spin-to-win-daily-freebie-54"
    },
    {
      "Source": "Phatlads",
      "Product": "Ends Tonight",
      "Price": "\u00a30.03",
      "Percent Sold": "",
      "Source URL": "",
      "URL": "https://phatlads.com/competitions/lucky-3-s-3"
    },
    {
      "Source": "Phatlads",
      "Product": "SOLD OUT",
      "Price": "\u00a30.00",
      "Percent Sold": "",
      "Source URL": "",
      "URL": "https://phatlads.com/competitions/free-limited-every-ticket-wins-bronze-6"
    },
    {
      "Source": "Powertoolmateprizes",
      "Product": "Apple Watch Ultra 3 Gps Cellular 49Mm 5782",
      "Price": "\u00a30.08",
      "Percent Sold": "",
      "Source URL": "",
      "URL": "https://ptmprizes.co.uk/apple-watch-ultra-3-gps--cellular-49mm---5782.htm"
    },
    {
      "Source": "Powertoolmateprizes",
      "Product": "C358Fab3C2E605B96Ed66Fe300A60Ca3 5783",
      "Price": "\u00a30.05",
      "Percent Sold": "",
      "Source URL": "",
      "URL": "https://ptmprizes.co.uk/c358fab3c2e605b96ed66fe300a60ca3--5783.htm"
    },
    {
      "Source": "Powertoolmateprizes",
      "Product": "Milwaukee M18Fophltkit2 0 18V Fuel Outdoor Power Head Kit Gen 2 Naked Quik Lok 5773",
      "Price": "\u00a30.28",
      "Percent Sold": "",
      "Source URL": "",
      "URL": "https://ptmprizes.co.uk/milwaukee-m18fophltkit2-0-18v-fuel-outdoor-power-head-kit-gen-2-naked-quik-lok--5773.htm"
    },
    {
      "Source": "Powertoolmateprizes",
      "Product": "Stabila Dark Shadow 4 Piece Level Set 40Cm 61Cm 122Cm 183Cm 5790",
      "Price": "\u00a30.02",
      "Percent Sold": "",
      "Source URL": "",
      "URL": "https://ptmprizes.co.uk/stabila-dark-shadow-4-piece-level-set---40cm--61cm--122cm--183cm--5790.htm"
    },
    {
      "Source": "Theguitarmarketplace",
      "Product": "Gibson 120th Anniversary Les Paul Traditional in Heritage Cherry Sunburst",
      "Price": "\u00a30.99",
      "Percent Sold": "38.98%",
      "Source URL": "",
      "URL": "https://theguitarmarketplace.com/competition/gibson-120th-anniversary-les-paul-traditional-in-heritage-cherry-sunburst-3/"
    },
    {
      "Source": "Timevault",
      "Product": "Seiko Prospex",
      "Price": "\u00a32.00",
      "Percent Sold": "5.57%",
      "Source URL": "",
      "URL": "https://timevault.ltd/competitions/seiko-pospex/"
    },
    {
      "Source": "Too Much",
      "Product": "Odds Accelerator #19 (\u00a3100 Site Credit End Prize)",
      "Price": "\u00a30.10",
      "Percent Sold": "95%",
      "Source URL": "",
      "URL": "https://toomuchcompetitions.co.uk/competition/odds-accelerator-19-100-site-credit-end-prize/"
    },
    {
      "Source": "Too Much",
      "Product": "Win 10 entries into Rolex \u201cRoot Beer\u201d on Sunday \u2013 Low Odds",
      "Price": "\u00a32.50",
      "Percent Sold": "27%",
      "Source URL": "",
      "URL": "https://toomuchcompetitions.co.uk/competition/win-10-entries-into-rolex-root-beer-on-sunday-low-odds/"
    },
    {
      "Source": "Too Much",
      "Product": "Win 10 entries into Rolex \u201cRoot Beer\u201d on Sunday \u2013 Ultra Low Odds",
      "Price": "\u00a35.00",
      "Percent Sold": "42%",
      "Source URL": "",
      "URL": "https://toomuchcompetitions.co.uk/competition/win-10-entries-into-rolex-root-beer-on-sunday-ultra-low-odds/"
    },
    {
      "Source": "Too Much",
      "Product": "Win 1g Real Gold Bar 999.9 Fine Gold",
      "Price": "\u00a31.00",
      "Percent Sold": "50%",
      "Source URL": "",
      "URL": "https://toomuchcompetitions.co.uk/competition/win-1g-real-gold-bar-999-9-fine-gold/"
    },
    {
      "Source": "Too Much",
      "Product": "Win 5 entries into Rolex \u201cRoot Beer\u201d on Sunday",
      "Price": "\u00a31.00",
      "Percent Sold": "46%",
      "Source URL": "",
      "URL": "https://toomuchcompetitions.co.uk/competition/win-5-entries-into-rolex-root-beer-on-sunday/"
    },
    {
      "Source": "Too Much",
      "Product": "Win this 2026 GMT-Master II \u201cRootbeer\u201d Bi-Metal 18K Everose Gold (\u00a314,000 Cash Alternative)",
      "Price": "\u00a340.00",
      "Percent Sold": "22%",
      "Source URL": "",
      "URL": "https://toomuchcompetitions.co.uk/competition/win-this-2026-gmt-master-ii-rootbeer-bi-metal-18k-everose-gold-14000-cash-alternative/"
    },
    {
      "Source": "Too Much",
      "Product": "Win this Tag Heuer Formula 1 Solargraph x Indy 500 \u2013 Limited Edition! (\u00a31,300 Cash Alternative)",
      "Price": "\u00a32.99",
      "Percent Sold": "22%",
      "Source URL": "",
      "URL": "https://toomuchcompetitions.co.uk/competition/win-this-tag-heuer-formula-1-solargraph-x-indy-500-limited-edition-1300-cash-alternative-2/"
    },
    {
      "Source": "Too Much",
      "Product": "Win this Tom Ford Oud Wood Eau De Parfum 30ml (\u00a3100 Cash Alt) #3",
      "Price": "\u00a31.20",
      "Percent Sold": "47%",
      "Source URL": "",
      "URL": "https://toomuchcompetitions.co.uk/competition/win-this-tom-ford-oud-wood-eau-de-parfum-30ml-100-cash-alt-3/"
    },
    {
      "Source": "Too Much",
      "Product": "Win \u00a310,000 Tax Free Cash on Sunday!",
      "Price": "\u00a31.00",
      "Percent Sold": "21%",
      "Source URL": "",
      "URL": "https://toomuchcompetitions.co.uk/competition/win-10000-tax-free-cash-on-sunday/"
    },
    {
      "Source": "Too Much",
      "Product": "Win \u00a3100 Site Credit #2",
      "Price": "\u00a30.05",
      "Percent Sold": "12%",
      "Source URL": "",
      "URL": "https://toomuchcompetitions.co.uk/competition/win-100-site-credit-2/"
    },
    {
      "Source": "Tradetoolgiveaways",
      "Product": "Auto Draw \u2013 Milwaukee PACKOUT Essentials Bundle #2",
      "Price": "\u00a30.01",
      "Percent Sold": "83%",
      "Source URL": "",
      "URL": "https://www.tradetoolgiveaways.co.uk/competition/auto-draw-milwaukee-packout-essentials-bundle-2/"
    },
    {
      "Source": "Tradetoolgiveaways",
      "Product": "Auto Draw \u2013 Ninja Perfect Temperature KT201UK Kettle with Temperature Selector \u2013 Stainless Steel #5",
      "Price": "\u00a30.01",
      "Percent Sold": "74%",
      "Source URL": "",
      "URL": "https://www.tradetoolgiveaways.co.uk/competition/auto-draw-ninja-perfect-temperature-kt201uk-kettle-with-temperature-selector-stainless-steel-5/"
    },
    {
      "Source": "Tradetoolgiveaways",
      "Product": "Auto Draw \u2013 NWS VDE 3 Piece Pliers Set & Fluke 1AC-II Non-Contact Voltage Tester #3",
      "Price": "\u00a30.01",
      "Percent Sold": "56%",
      "Source URL": "",
      "URL": "https://www.tradetoolgiveaways.co.uk/competition/auto-draw-nws-vde-3-piece-pliers-set-fluke-1ac-ii-non-contact-voltage-tester-3/"
    },
    {
      "Source": "Tradetoolgiveaways",
      "Product": "Auto Draw \u2013 Snowdonia Cheese Co Decadent Cheese Hamper + Round Slate Serving Board #3",
      "Price": "\u00a30.01",
      "Percent Sold": "46%",
      "Source URL": "",
      "URL": "https://www.tradetoolgiveaways.co.uk/competition/auto-draw-snowdonia-cheese-co-decadent-cheese-hamper-round-slate-serving-board-3/"
    },
    {
      "Source": "UK Minis",
      "Product": "362 BHP Diminutive Resto mod Mini (Exeter) Or \u00a340k Cash",
      "Price": "\u00a30.99",
      "Percent Sold": "64%",
      "Source URL": "",
      "URL": "https://ukminis.co.uk/competition/362-bhp-diminutive-resto-mod-mini-exeter-or-40k-cash"
    },
    {
      "Source": "Ukcc",
      "Product": "2024 VW TRANSPORTER CAMPER T6.1 + VW TOUAREG R-LINE + \u00a35,000!",
      "Price": "\u00a30.29",
      "Percent Sold": "61%",
      "Source URL": "",
      "URL": "https://ukcc.co.uk/competition/vwttc"
    },
    {
      "Source": "Ukcc",
      "Product": "FREE ENTRY - WIN \u00a3100 | SPEND \u00a31- \u00a35+ & WIN EXTRA CASH!",
      "Price": "\u00a30.00",
      "Percent Sold": "100%",
      "Source URL": "",
      "URL": "https://ukcc.co.uk/competition/freecomp1442"
    },
    {
      "Source": "Ukcc",
      "Product": "FREE ENTRY - WIN \u00a3100 | SPEND \u00a31-\u00a35+ AND WIN THIS LAY-Z-SPA IBIZA AIRJET & CASH!",
      "Price": "\u00a30.00",
      "Percent Sold": "53%",
      "Source URL": "",
      "URL": "https://ukcc.co.uk/competition/freecomp1443"
    },
    {
      "Source": "Ukcc",
      "Product": "IPHONE 17 PRO MAX!",
      "Price": "\u00a30.20",
      "Percent Sold": "17%",
      "Source URL": "",
      "URL": "https://ukcc.co.uk/competition/iphone-17-pro-max-3"
    },
    {
      "Source": "Ukcc",
      "Product": "THE GRAND CASH HEIST!",
      "Price": "\u00a30.10",
      "Percent Sold": "9%",
      "Source URL": "",
      "URL": "https://ukcc.co.uk/competition/the-grand-cash-heist"
    },
    {
      "Source": "Ukcc",
      "Product": "THE NINJA DUO - SUMMER EDITION!",
      "Price": "\u00a30.01",
      "Percent Sold": "16%",
      "Source URL": "",
      "URL": "https://ukcc.co.uk/competition/the-ninja-duo-summer-edition-3"
    },
    {
      "Source": "Ukcc",
      "Product": "\u00a3100 CASH!",
      "Price": "\u00a30.50",
      "Percent Sold": "91%",
      "Source URL": "",
      "URL": "https://ukcc.co.uk/competition/100-cash-14"
    },
    {
      "Source": "Ukcc",
      "Product": "\u00a3200 CASH!",
      "Price": "\u00a30.90",
      "Percent Sold": "96%",
      "Source URL": "",
      "URL": "https://ukcc.co.uk/competition/200-cash-7"
    },
    {
      "Source": "Ukcc",
      "Product": "\u00a325 SITE CREDIT!",
      "Price": "\u00a30.01",
      "Percent Sold": "100%",
      "Source URL": "",
      "URL": "https://ukcc.co.uk/competition/25-site-credit-15"
    },
    {
      "Source": "Ukcc",
      "Product": "\u00a35.00 'WIN MORE' RAFFLE!",
      "Price": "\u00a35.00",
      "Percent Sold": "44%",
      "Source URL": "",
      "URL": "https://ukcc.co.uk/competition/newwin"
    },
    {
      "Source": "Ukcc",
      "Product": "\u00a350 SITE CREDIT!",
      "Price": "\u00a30.05",
      "Percent Sold": "100%",
      "Source URL": "",
      "URL": "https://ukcc.co.uk/competition/50-site-credit-16"
    },
    {
      "Source": "Unleashed Competitions",
      "Product": "50 Fridge Filler",
      "Price": "\u00a3 0.50",
      "Percent Sold": "85%",
      "Source URL": "",
      "URL": "https://unleashed-competitions.com/product/50-fridge-filler/"
    },
    {
      "Source": "Unleashed Competitions",
      "Product": "50 Worth Of Crisps",
      "Price": "\u00a3 0.99",
      "Percent Sold": "96%",
      "Source URL": "",
      "URL": "https://unleashed-competitions.com/product/50-worth-of-crisps/"
    },
    {
      "Source": "Xtreme",
      "Product": "WIN 10X ENTRIES TO THE STARK VARG EX DRAW#10",
      "Price": "\u00a30.99",
      "Percent Sold": "",
      "Source URL": "",
      "URL": "https://xtreme-competitions.co.uk/product/win-10x-entries-to-the-stark-varg-ex-draw10/"
    },
    {
      "Source": "Xtreme",
      "Product": "WIN 10X ENTRIES TO THE STARK VARG EX DRAW#9",
      "Price": "\u00a30.99",
      "Percent Sold": "",
      "Source URL": "",
      "URL": "https://xtreme-competitions.co.uk/product/win-10x-entries-to-the-stark-varg-ex-draw9/"
    },
    {
      "Source": "Xtreme",
      "Product": "WIN THIS BRAND NEW 80HP ROAD LEGAL STARK VARG EX",
      "Price": "\u00a325.00",
      "Percent Sold": "",
      "Source URL": "",
      "URL": "https://xtreme-competitions.co.uk/product/win-this-custom-80hp-road-legal-stark-varg-ex/"
    }
  ]
}